nonebot_plugin_push/__init__.py
nonebot_plugin_push/config.py
nonebot_plugin_push/message.py
nonebot_plugin_push/model.py
nonebot_plugin_push/platforms/__init__.py
nonebot_plugin_push/platforms/base.py
nonebot_plugin_push/platforms/feishu.py
nonebot_plugin_push/platforms/mail.py
nonebot_plugin_push/status.py
nonebot_plugin_push-0.1.0.dist-info/LICENSE
nonebot_plugin_push-0.1.0.dist-info/METADATA
nonebot_plugin_push-0.1.0.dist-info/WHEEL
nonebot_plugin_push-0.1.0.dist-info/RECORD
