Metadata-Version: 2.1
Name: nonebot-plugin-push
Version: 0.1.0
Summary: 消息推送插件
Home-page: https://github.com/mobyw/nonebot-plugin-push
License: MIT
Keywords: nonebot2,plugin,push
Author: mobyw
Author-email: mobyw66@gmail.com
Requires-Python: >=3.8,<4.0
Classifier: License :: OSI Approved :: MIT License
Classifier: Programming Language :: Python :: 3
Classifier: Programming Language :: Python :: 3.8
Classifier: Programming Language :: Python :: 3.9
Classifier: Programming Language :: Python :: 3.10
Classifier: Programming Language :: Python :: 3.11
Requires-Dist: aiosmtplib (>=2.0.2,<3.0.0)
Requires-Dist: markdown (>=3.4.4,<4.0.0)
Requires-Dist: nonebot2[fastapi,httpx] (>=2.0.1,<3.0.0)
Requires-Dist: pydantic[email] (>=1.10.0,<2.0.0)
Project-URL: Documentation, https://github.com/mobyw/nonebot-plugin-push/blob/main/README.md
Project-URL: Repository, https://github.com/mobyw/nonebot-plugin-push
